{
  "nm": "02 Lipstick",
  "ddd": 0,
  "h": 500,
  "w": 500,
  "meta": {
    "g": "@lottiefiles/toolkit-js 0.33.2"
  },
  "layers": [
    {
      "ty": 3,
      "nm": "Main Stroke width - Color Ctrl",
      "sr": 1,
      "st": 0,
      "op": 120,
      "ip": 0,
      "hd": false,
      "ddd": 0,
      "bm": 0,
      "hasMask": false,
      "ao": 0,
      "ks": {
        "a": {
          "a": 0,
          "k": [
            50,
            50,
            0
          ],
          "ix": 1
        },
        "s": {
          "a": 0,
          "k": [
            100,
            100,
            100
          ],
          "ix": 6
        },
        "sk": {
          "a": 0,
          "k": 0
        },
        "p": {
          "a": 0,
          "k": [
            0,
            0,
            0
          ],
          "ix": 2
        },
        "r": {
          "a": 0,
          "k": 0,
          "ix": 10
        },
        "sa": {
          "a": 0,
          "k": 0
        },
        "o": {
          "a": 0,
          "k": 0,
          "ix": 11
        }
      },
      "ef": [
        {
          "ty": 5,
          "nm": "Stroke width",
          "ix": 1,
          "en": 1,
          "ef": [
            {
              "ty": 0,
              "nm": "Slider",
              "ix": 1,
              "v": {
                "a": 0,
                "k": 16,
                "ix": 1
              }
            }
          ]
        }
      ],
      "ind": 1,
      "parent": 9
    },
    {
      "ty": 4,
      "nm": "Line 2",
      "sr": 1,
      "st": 51,
      "op": 153,
      "ip": 51,
      "hd": false,
      "ddd": 0,
      "bm": 0,
      "hasMask": false,
      "ao": 0,
      "ks": {
        "a": {
          "a": 0,
          "k": [
            0,
            -169.97,
            0
          ],
          "ix": 1
        },
        "s": {
          "a": 0,
          "k": [
            100,
            100,
            100
          ],
          "ix": 6
        },
        "sk": {
          "a": 0,
          "k": 0
        },
        "p": {
          "a": 0,
          "k": [
            50,
            -157.97,
            0
          ],
          "ix": 2
        },
        "r": {
          "a": 0,
          "k": 0,
          "ix": 10
        },
        "sa": {
          "a": 0,
          "k": 0
        },
        "o": {
          "a": 0,
          "k": 100,
          "ix": 11
        }
      },
      "ef": [],
      "shapes": [
        {
          "ty": "gr",
          "bm": 0,
          "hd": false,
          "nm": "Group 3",
          "ix": 1,
          "cix": 2,
          "it": [
            {
              "ty": "sh",
              "bm": 0,
              "hd": false,
              "nm": "Path 1",
              "ix": 1,
              "d": 1,
              "ks": {
                "a": 0,
                "k": {
                  "c": false,
                  "i": [
                    [
                      0,
                      0
                    ],
                    [
                      0,
                      0
                    ]
                  ],
                  "o": [
                    [
                      0,
                      0
                    ],
                    [
                      0,
                      0
                    ]
                  ],
                  "v": [
                    [
                      64.696,
                      -156.19
                    ],
                    [
                      48.522,
                      -140.016
                    ]
                  ]
                },
                "ix": 2
              }
            },
            {
              "ty": "st",
              "bm": 0,
              "hd": false,
              "nm": "Stroke 1",
              "lc": 2,
              "lj": 2,
              "ml": 1,
              "o": {
                "a": 0,
                "k": 100,
                "ix": 4
              },
              "w": {
                "a": 0,
                "k": 16,
                "ix": 5,
                "x": "var $bm_rt;\n$bm_rt = thisComp.layer('Main Stroke width - Color Ctrl').effect('Stroke width')('Slider');"
              },
              "c": {
                "a": 0,
                "k": [
                  1,
                  1,
                  1
                ],
                "ix": 3
              }
            },
            {
              "ty": "tr",
              "a": {
                "a": 0,
                "k": [
                  0,
                  0
                ],
                "ix": 1
              },
              "s": {
                "a": 0,
                "k": [
                  100,
                  100
                ],
                "ix": 3
              },
              "sk": {
                "a": 0,
                "k": 0,
                "ix": 4
              },
              "p": {
                "a": 0,
                "k": [
                  0,
                  0
                ],
                "ix": 2
              },
              "r": {
                "a": 0,
                "k": 0,
                "ix": 6
              },
              "sa": {
                "a": 0,
                "k": 0,
                "ix": 5
              },
              "o": {
                "a": 0,
                "k": 100,
                "ix": 7
              }
            }
          ]
        },
        {
          "ty": "gr",
          "bm": 0,
          "hd": false,
          "nm": "Group 1",
          "ix": 2,
          "cix": 2,
          "it": [
            {
              "ty": "sh",
              "bm": 0,
              "hd": false,
              "nm": "Path 1",
              "ix": 1,
              "d": 1,
              "ks": {
                "a": 0,
                "k": {
                  "c": false,
                  "i": [
                    [
                      0,
                      0
                    ],
                    [
                      0,
                      0
                    ]
                  ],
                  "o": [
                    [
                      0,
                      0
                    ],
                    [
                      0,
                      0
                    ]
                  ],
                  "v": [
                    [
                      0,
                      -183.75
                    ],
                    [
                      0,
                      -160.114
                    ]
                  ]
                },
                "ix": 2
              }
            },
            {
              "ty": "st",
              "bm": 0,
              "hd": false,
              "nm": "Stroke 1",
              "lc": 2,
              "lj": 2,
              "ml": 1,
              "o": {
                "a": 0,
                "k": 100,
                "ix": 4
              },
              "w": {
                "a": 0,
                "k": 16,
                "ix": 5,
                "x": "var $bm_rt;\n$bm_rt = thisComp.layer('Main Stroke width - Color Ctrl').effect('Stroke width')('Slider');"
              },
              "c": {
                "a": 0,
                "k": [
                  1,
                  1,
                  1
                ],
                "ix": 3
              }
            },
            {
              "ty": "tr",
              "a": {
                "a": 0,
                "k": [
                  0,
                  0
                ],
                "ix": 1
              },
              "s": {
                "a": 0,
                "k": [
                  100,
                  100
                ],
                "ix": 3
              },
              "sk": {
                "a": 0,
                "k": 0,
                "ix": 4
              },
              "p": {
                "a": 0,
                "k": [
                  0,
                  0
                ],
                "ix": 2
              },
              "r": {
                "a": 0,
                "k": 0,
                "ix": 6
              },
              "sa": {
                "a": 0,
                "k": 0,
                "ix": 5
              },
              "o": {
                "a": 0,
                "k": 100,
                "ix": 7
              }
            }
          ]
        },
        {
          "ty": "gr",
          "bm": 0,
          "hd": false,
          "nm": "Group 2",
          "ix": 3,
          "cix": 2,
          "it": [
            {
              "ty": "sh",
              "bm": 0,
              "hd": false,
              "nm": "Path 1",
              "ix": 1,
              "d": 1,
              "ks": {
                "a": 0,
                "k": {
                  "c": false,
                  "i": [
                    [
                      0,
                      0
                    ],
                    [
                      0,
                      0
                    ]
                  ],
                  "o": [
                    [
                      0,
                      0
                    ],
                    [
                      0,
                      0
                    ]
                  ],
                  "v": [
                    [
                      -64.696,
                      -156.19
                    ],
                    [
                      -48.522,
                      -140.016
                    ]
                  ]
                },
                "ix": 2
              }
            },
            {
              "ty": "st",
              "bm": 0,
              "hd": false,
              "nm": "Stroke 1",
              "lc": 2,
              "lj": 2,
              "ml": 1,
              "o": {
                "a": 0,
                "k": 100,
                "ix": 4
              },
              "w": {
                "a": 0,
                "k": 16,
                "ix": 5,
                "x": "var $bm_rt;\n$bm_rt = thisComp.layer('Main Stroke width - Color Ctrl').effect('Stroke width')('Slider');"
              },
              "c": {
                "a": 0,
                "k": [
                  1,
                  1,
                  1
                ],
                "ix": 3
              }
            },
            {
              "ty": "tr",
              "a": {
                "a": 0,
                "k": [
                  0,
                  0
                ],
                "ix": 1
              },
              "s": {
                "a": 0,
                "k": [
                  100,
                  100
                ],
                "ix": 3
              },
              "sk": {
                "a": 0,
                "k": 0,
                "ix": 4
              },
              "p": {
                "a": 0,
                "k": [
                  0,
                  0
                ],
                "ix": 2
              },
              "r": {
                "a": 0,
                "k": 0,
                "ix": 6
              },
              "sa": {
                "a": 0,
                "k": 0,
                "ix": 5
              },
              "o": {
                "a": 0,
                "k": 100,
                "ix": 7
              }
            }
          ]
        },
        {
          "ty": "tm",
          "bm": 0,
          "hd": false,
          "nm": "Trim Paths 1",
          "ix": 4,
          "e": {
            "a": 1,
            "k": [
              {
                "o": {
                  "x": 0.26,
                  "y": 0
                },
                "i": {
                  "x": 0.74,
                  "y": 1
                },
                "s": [
                  100
                ],
                "t": 80
              },
              {
                "s": [
                  0
                ],
                "t": 106
              }
            ],
            "ix": 2
          },
          "o": {
            "a": 0,
            "k": 0,
            "ix": 3
          },
          "s": {
            "a": 1,
            "k": [
              {
                "o": {
                  "x": 0.26,
                  "y": 0
                },
                "i": {
                  "x": 0.74,
                  "y": 1
                },
                "s": [
                  100
                ],
                "t": 74
              },
              {
                "s": [
                  0
                ],
                "t": 102
              }
            ],
            "ix": 1
          },
          "m": 2
        }
      ],
      "ind": 2,
      "parent": 1
    },
    {
      "ty": 4,
      "nm": "Line 1",
      "sr": 1,
      "st": 25,
      "op": 110,
      "ip": 25,
      "hd": false,
      "ddd": 0,
      "bm": 0,
      "hasMask": false,
      "ao": 0,
      "ks": {
        "a": {
          "a": 0,
          "k": [
            161.929,
            -175.636,
            0
          ],
          "ix": 1
        },
        "s": {
          "a": 0,
          "k": [
            -100,
            100,
            100
          ],
          "ix": 6
        },
        "sk": {
          "a": 0,
          "k": 0
        },
        "p": {
          "a": 0,
          "k": [
            -27.482,
            34.837,
            0
          ],
          "ix": 2
        },
        "r": {
          "a": 0,
          "k": -100.937,
          "ix": 10
        },
        "sa": {
          "a": 0,
          "k": 0
        },
        "o": {
          "a": 0,
          "k": 100,
          "ix": 11
        }
      },
      "ef": [],
      "shapes": [
        {
          "ty": "gr",
          "bm": 0,
          "hd": false,
          "nm": "Shape 1",
          "ix": 1,
          "cix": 2,
          "it": [
            {
              "ty": "sh",
              "bm": 0,
              "hd": false,
              "nm": "Path 1",
              "ix": 1,
              "d": 1,
              "ks": {
                "a": 0,
                "k": {
                  "c": false,
                  "i": [
                    [
                      0,
                      0
                    ],
                    [
                      47.24,
                      -111.437
                    ]
                  ],
                  "o": [
                    [
                      0,
                      0
                    ],
                    [
                      -34.739,
                      81.946
                    ]
                  ],
                  "v": [
                    [
                      130.585,
                      -233.673
                    ],
                    [
                      162.537,
                      -54.621
                    ]
                  ]
                },
                "ix": 2
              }
            },
            {
              "ty": "st",
              "bm": 0,
              "hd": false,
              "nm": "Stroke 1",
              "lc": 2,
              "lj": 1,
              "ml": 4,
              "o": {
                "a": 0,
                "k": 100,
                "ix": 4
              },
              "w": {
                "a": 0,
                "k": 16,
                "ix": 5,
                "x": "var $bm_rt;\n$bm_rt = thisComp.layer('Main Stroke width - Color Ctrl').effect('Stroke width')('Slider');"
              },
              "c": {
                "a": 0,
                "k": [
                  1,
                  0.149,
                  0.8
                ],
                "ix": 3
              }
            },
            {
              "ty": "tr",
              "a": {
                "a": 0,
                "k": [
                  0,
                  0
                ],
                "ix": 1
              },
              "s": {
                "a": 0,
                "k": [
                  100,
                  100
                ],
                "ix": 3
              },
              "sk": {
                "a": 0,
                "k": 0,
                "ix": 4
              },
              "p": {
                "a": 0,
                "k": [
                  0,
                  0
                ],
                "ix": 2
              },
              "r": {
                "a": 0,
                "k": 0,
                "ix": 6
              },
              "sa": {
                "a": 0,
                "k": 0,
                "ix": 5
              },
              "o": {
                "a": 0,
                "k": 100,
                "ix": 7
              }
            }
          ]
        },
        {
          "ty": "tm",
          "bm": 0,
          "hd": false,
          "nm": "Trim Paths 1",
          "ix": 2,
          "e": {
            "a": 1,
            "k": [
              {
                "o": {
                  "x": 0.21,
                  "y": 0
                },
                "i": {
                  "x": 0.79,
                  "y": 1
                },
                "s": [
                  0
                ],
                "t": 27
              },
              {
                "s": [
                  100
                ],
                "t": 47.002
              }
            ],
            "ix": 2
          },
          "o": {
            "a": 0,
            "k": 0,
            "ix": 3
          },
          "s": {
            "a": 1,
            "k": [
              {
                "o": {
                  "x": 0.21,
                  "y": 0
                },
                "i": {
                  "x": 0.79,
                  "y": 1
                },
                "s": [
                  0
                ],
                "t": 35
              },
              {
                "s": [
                  100
                ],
                "t": 55
              }
            ],
            "ix": 1
          },
          "m": 1
        }
      ],
      "ind": 3,
      "parent": 4
    },
    {
      "ty": 4,
      "nm": "Base",
      "sr": 1,
      "st": 0,
      "op": 120,
      "ip": 0,
      "hd": false,
      "ddd": 0,
      "bm": 0,
      "hasMask": false,
      "ao": 0,
      "ks": {
        "a": {
          "a": 0,
          "k": [
            0,
            183.75,
            0
          ],
          "ix": 1
        },
        "s": {
          "a": 0,
          "k": [
            100,
            100,
            100
          ],
          "ix": 6
        },
        "sk": {
          "a": 0,
          "k": 0
        },
        "p": {
          "a": 0,
          "k": [
            50,
            233.75,
            0
          ],
          "ix": 2
        },
        "r": {
          "a": 1,
          "k": [
            {
              "o": {
                "x": 0.31,
                "y": 0
              },
              "i": {
                "x": 0.69,
                "y": 1
              },
              "s": [
                0
              ],
              "t": 0
            },
            {
              "o": {
                "x": 0.31,
                "y": 0
              },
              "i": {
                "x": 0.69,
                "y": 1
              },
              "s": [
                -21.024
              ],
              "t": 28
            },
            {
              "o": {
                "x": 0.31,
                "y": 0
              },
              "i": {
                "x": 0.69,
                "y": 1
              },
              "s": [
                10
              ],
              "t": 47
            },
            {
              "o": {
                "x": 0.31,
                "y": 0
              },
              "i": {
                "x": 0.69,
                "y": 1
              },
              "s": [
                -5
              ],
              "t": 62
            },
            {
              "o": {
                "x": 0.31,
                "y": 0
              },
              "i": {
                "x": 0.69,
                "y": 1
              },
              "s": [
                2.5
              ],
              "t": 73
            },
            {
              "s": [
                0
              ],
              "t": 83
            }
          ],
          "ix": 10
        },
        "sa": {
          "a": 0,
          "k": 0
        },
        "o": {
          "a": 0,
          "k": 100,
          "ix": 11
        }
      },
      "ef": [],
      "shapes": [
        {
          "ty": "gr",
          "bm": 0,
          "hd": false,
          "nm": "Group 1",
          "ix": 1,
          "cix": 2,
          "it": [
            {
              "ty": "sh",
              "bm": 0,
              "hd": false,
              "nm": "Path 1",
              "ix": 1,
              "d": 1,
              "ks": {
                "a": 0,
                "k": {
                  "c": true,
                  "i": [
                    [
                      0,
                      0
                    ],
                    [
                      0,
                      0
                    ],
                    [
                      0,
                      0
                    ],
                    [
                      0,
                      0
                    ]
                  ],
                  "o": [
                    [
                      0,
                      0
                    ],
                    [
                      0,
                      0
                    ],
                    [
                      0,
                      0
                    ],
                    [
                      0,
                      0
                    ]
                  ],
                  "v": [
                    [
                      43.078,
                      -62.671
                    ],
                    [
                      -42.316,
                      -62.671
                    ],
                    [
                      -42.316,
                      30.498
                    ],
                    [
                      43.078,
                      30.498
                    ]
                  ]
                },
                "ix": 2
              }
            },
            {
              "ty": "st",
              "bm": 0,
              "hd": false,
              "nm": "Stroke 1",
              "lc": 2,
              "lj": 2,
              "ml": 1,
              "o": {
                "a": 0,
                "k": 100,
                "ix": 4
              },
              "w": {
                "a": 0,
                "k": 16,
                "ix": 5,
                "x": "var $bm_rt;\n$bm_rt = thisComp.layer('Main Stroke width - Color Ctrl').effect('Stroke width')('Slider');"
              },
              "c": {
                "a": 0,
                "k": [
                  1,
                  1,
                  1
                ],
                "ix": 3
              }
            },
            {
              "ty": "tr",
              "a": {
                "a": 0,
                "k": [
                  0,
                  0
                ],
                "ix": 1
              },
              "s": {
                "a": 0,
                "k": [
                  100,
                  100
                ],
                "ix": 3
              },
              "sk": {
                "a": 0,
                "k": 0,
                "ix": 4
              },
              "p": {
                "a": 0,
                "k": [
                  0,
                  0
                ],
                "ix": 2
              },
              "r": {
                "a": 0,
                "k": 0,
                "ix": 6
              },
              "sa": {
                "a": 0,
                "k": 0,
                "ix": 5
              },
              "o": {
                "a": 0,
                "k": 100,
                "ix": 7
              }
            }
          ]
        },
        {
          "ty": "gr",
          "bm": 0,
          "hd": false,
          "nm": "Group 2",
          "ix": 2,
          "cix": 2,
          "it": [
            {
              "ty": "sh",
              "bm": 0,
              "hd": false,
              "nm": "Path 1",
              "ix": 1,
              "d": 1,
              "ks": {
                "a": 0,
                "k": {
                  "c": true,
                  "i": [
                    [
                      0,
                      0
                    ],
                    [
                      0,
                      0
                    ],
                    [
                      0,
                      0
                    ],
                    [
                      0,
                      0
                    ]
                  ],
                  "o": [
                    [
                      0,
                      0
                    ],
                    [
                      0,
                      0
                    ],
                    [
                      0,
                      0
                    ],
                    [
                      0,
                      0
                    ]
                  ],
                  "v": [
                    [
                      67.477,
                      73.195
                    ],
                    [
                      -66.714,
                      73.195
                    ],
                    [
                      -54.515,
                      30.498
                    ],
                    [
                      55.277,
                      30.498
                    ]
                  ]
                },
                "ix": 2
              }
            },
            {
              "ty": "st",
              "bm": 0,
              "hd": false,
              "nm": "Stroke 1",
              "lc": 2,
              "lj": 2,
              "ml": 1,
              "o": {
                "a": 0,
                "k": 100,
                "ix": 4
              },
              "w": {
                "a": 0,
                "k": 16,
                "ix": 5,
                "x": "var $bm_rt;\n$bm_rt = thisComp.layer('Main Stroke width - Color Ctrl').effect('Stroke width')('Slider');"
              },
              "c": {
                "a": 0,
                "k": [
                  1,
                  1,
                  1
                ],
                "ix": 3
              }
            },
            {
              "ty": "tr",
              "a": {
                "a": 0,
                "k": [
                  0,
                  0
                ],
                "ix": 1
              },
              "s": {
                "a": 0,
                "k": [
                  100,
                  100
                ],
                "ix": 3
              },
              "sk": {
                "a": 0,
                "k": 0,
                "ix": 4
              },
              "p": {
                "a": 0,
                "k": [
                  0,
                  0
                ],
                "ix": 2
              },
              "r": {
                "a": 0,
                "k": 0,
                "ix": 6
              },
              "sa": {
                "a": 0,
                "k": 0,
                "ix": 5
              },
              "o": {
                "a": 0,
                "k": 100,
                "ix": 7
              }
            }
          ]
        },
        {
          "ty": "gr",
          "bm": 0,
          "hd": false,
          "nm": "Group 3",
          "ix": 3,
          "cix": 2,
          "it": [
            {
              "ty": "sh",
              "bm": 0,
              "hd": false,
              "nm": "Path 1",
              "ix": 1,
              "d": 1,
              "ks": {
                "a": 0,
                "k": {
                  "c": true,
                  "i": [
                    [
                      16.844,
                      0
                    ],
                    [
                      0,
                      0
                    ],
                    [
                      0,
                      16.844
                    ],
                    [
                      0,
                      0
                    ],
                    [
                      0,
                      0
                    ],
                    [
                      0,
                      0
                    ]
                  ],
                  "o": [
                    [
                      0,
                      0
                    ],
                    [
                      -16.844,
                      0
                    ],
                    [
                      0,
                      0
                    ],
                    [
                      0,
                      0
                    ],
                    [
                      0,
                      0
                    ],
                    [
                      0,
                      16.844
                    ]
                  ],
                  "v": [
                    [
                      49.178,
                      183.75
                    ],
                    [
                      -49.178,
                      183.75
                    ],
                    [
                      -79.676,
                      153.252
                    ],
                    [
                      -79.676,
                      73.195
                    ],
                    [
                      79.676,
                      73.195
                    ],
                    [
                      79.676,
                      153.252
                    ]
                  ]
                },
                "ix": 2
              }
            },
            {
              "ty": "st",
              "bm": 0,
              "hd": false,
              "nm": "Stroke 1",
              "lc": 2,
              "lj": 2,
              "ml": 1,
              "o": {
                "a": 0,
                "k": 100,
                "ix": 4
              },
              "w": {
                "a": 0,
                "k": 16,
                "ix": 5,
                "x": "var $bm_rt;\n$bm_rt = thisComp.layer('Main Stroke width - Color Ctrl').effect('Stroke width')('Slider');"
              },
              "c": {
                "a": 0,
                "k": [
                  1,
                  1,
                  1
                ],
                "ix": 3
              }
            },
            {
              "ty": "tr",
              "a": {
                "a": 0,
                "k": [
                  0,
                  0
                ],
                "ix": 1
              },
              "s": {
                "a": 0,
                "k": [
                  100,
                  100
                ],
                "ix": 3
              },
              "sk": {
                "a": 0,
                "k": 0,
                "ix": 4
              },
              "p": {
                "a": 0,
                "k": [
                  0,
                  0
                ],
                "ix": 2
              },
              "r": {
                "a": 0,
                "k": 0,
                "ix": 6
              },
              "sa": {
                "a": 0,
                "k": 0,
                "ix": 5
              },
              "o": {
                "a": 0,
                "k": 100,
                "ix": 7
              }
            }
          ]
        }
      ],
      "ind": 4,
      "parent": 1
    },
    {
      "ty": 4,
      "nm": "Lipstick 2",
      "sr": 1,
      "st": 0,
      "op": 120,
      "ip": 0,
      "hd": false,
      "ddd": 0,
      "bm": 0,
      "hasMask": false,
      "td": 1,
      "ao": 0,
      "ks": {
        "a": {
          "a": 0,
          "k": [
            0,
            0,
            0
          ],
          "ix": 1
        },
        "s": {
          "a": 0,
          "k": [
            100,
            100,
            100
          ],
          "ix": 6
        },
        "sk": {
          "a": 0,
          "k": 0
        },
        "p": {
          "a": 0,
          "k": [
            0,
            0,
            0
          ],
          "ix": 2
        },
        "r": {
          "a": 0,
          "k": 0,
          "ix": 10
        },
        "sa": {
          "a": 0,
          "k": 0
        },
        "o": {
          "a": 0,
          "k": 100,
          "ix": 11
        }
      },
      "ef": [],
      "shapes": [
        {
          "ty": "gr",
          "bm": 0,
          "hd": false,
          "nm": "Group 1",
          "ix": 1,
          "cix": 2,
          "it": [
            {
              "ty": "sh",
              "bm": 0,
              "hd": false,
              "nm": "Path 1",
              "ix": 1,
              "d": 1,
              "ks": {
                "a": 1,
                "k": [
                  {
                    "o": {
                      "x": 0.167,
                      "y": 0.167
                    },
                    "i": {
                      "x": 0.833,
                      "y": 0.833
                    },
                    "s": [
                      {
                        "c": true,
                        "i": [
                          [
                            0,
                            0
                          ],
                          [
                            0,
                            0
                          ],
                          [
                            0,
                            0
                          ],
                          [
                            0,
                            0
                          ]
                        ],
                        "o": [
                          [
                            0,
                            0
                          ],
                          [
                            0,
                            0
                          ],
                          [
                            0,
                            0
                          ],
                          [
                            0,
                            0
                          ]
                        ],
                        "v": [
                          [
                            -30.117,
                            -62.671
                          ],
                          [
                            -30.117,
                            -183.75
                          ],
                          [
                            30.879,
                            -158.589
                          ],
                          [
                            30.879,
                            -62.671
                          ]
                        ]
                      }
                    ],
                    "t": 0
                  },
                  {
                    "o": {
                      "x": 0.167,
                      "y": 0.167
                    },
                    "i": {
                      "x": 0.833,
                      "y": 0.833
                    },
                    "s": [
                      {
                        "c": true,
                        "i": [
                          [
                            0,
                            0
                          ],
                          [
                            0,
                            0
                          ],
                          [
                            0,
                            0
                          ],
                          [
                            0,
                            0
                          ]
                        ],
                        "o": [
                          [
                            0,
                            0
                          ],
                          [
                            0,
                            0
                          ],
                          [
                            0,
                            0
                          ],
                          [
                            0,
                            0
                          ]
                        ],
                        "v": [
                          [
                            -30.117,
                            -62.671
                          ],
                          [
                            -30.154,
                            -171.375
                          ],
                          [
                            30.84,
                            -166.464
                          ],
                          [
                            30.879,
                            -62.671
                          ]
                        ]
                      }
                    ],
                    "t": 28
                  },
                  {
                    "o": {
                      "x": 0.167,
                      "y": 0.167
                    },
                    "i": {
                      "x": 0.833,
                      "y": 0.833
                    },
                    "s": [
                      {
                        "c": true,
                        "i": [
                          [
                            0,
                            0
                          ],
                          [
                            0,
                            0
                          ],
                          [
                            0,
                            0
                          ],
                          [
                            0,
                            0
                          ]
                        ],
                        "o": [
                          [
                            0,
                            0
                          ],
                          [
                            0,
                            0
                          ],
                          [
                            0,
                            0
                          ],
                          [
                            0,
                            0
                          ]
                        ],
                        "v": [
                          [
                            -30.117,
                            -62.671
                          ],
                          [
                            -30.117,
                            -183.75
                          ],
                          [
                            30.879,
                            -158.589
                          ],
                          [
                            30.879,
                            -62.671
                          ]
                        ]
                      }
                    ],
                    "t": 47
                  },
                  {
                    "o": {
                      "x": 0.167,
                      "y": 0.167
                    },
                    "i": {
                      "x": 0.833,
                      "y": 0.833
                    },
                    "s": [
                      {
                        "c": true,
                        "i": [
                          [
                            0,
                            0
                          ],
                          [
                            0,
                            0
                          ],
                          [
                            0,
                            0
                          ],
                          [
                            0,
                            0
                          ]
                        ],
                        "o": [
                          [
                            0,
                            0
                          ],
                          [
                            0,
                            0
                          ],
                          [
                            0,
                            0
                          ],
                          [
                            0,
                            0
                          ]
                        ],
                        "v": [
                          [
                            -30.117,
                            -62.671
                          ],
                          [
                            -30.233,
                            -145.25
                          ],
                          [
                            30.758,
                            -183.089
                          ],
                          [
                            30.879,
                            -62.671
                          ]
                        ]
                      }
                    ],
                    "t": 62
                  },
                  {
                    "s": [
                      {
                        "c": true,
                        "i": [
                          [
                            0,
                            0
                          ],
                          [
                            0,
                            0
                          ],
                          [
                            0,
                            0
                          ],
                          [
                            0,
                            0
                          ]
                        ],
                        "o": [
                          [
                            0,
                            0
                          ],
                          [
                            0,
                            0
                          ],
                          [
                            0,
                            0
                          ],
                          [
                            0,
                            0
                          ]
                        ],
                        "v": [
                          [
                            -30.117,
                            -62.671
                          ],
                          [
                            -30.117,
                            -183.75
                          ],
                          [
                            30.879,
                            -158.589
                          ],
                          [
                            30.879,
                            -62.671
                          ]
                        ]
                      }
                    ],
                    "t": 83
                  }
                ],
                "ix": 2
              }
            },
            {
              "ty": "st",
              "bm": 0,
              "hd": false,
              "nm": "Stroke 1",
              "lc": 2,
              "lj": 2,
              "ml": 1,
              "o": {
                "a": 0,
                "k": 100,
                "ix": 4
              },
              "w": {
                "a": 0,
                "k": 16,
                "ix": 5,
                "x": "var $bm_rt;\n$bm_rt = $bm_sub(thisComp.layer('Main Stroke width - Color Ctrl').effect('Stroke width')('Slider'), 1);"
              },
              "c": {
                "a": 0,
                "k": [
                  1,
                  0.149,
                  0.8
                ],
                "ix": 3
              }
            },
            {
              "ty": "tr",
              "a": {
                "a": 0,
                "k": [
                  0,
                  0
                ],
                "ix": 1
              },
              "s": {
                "a": 0,
                "k": [
                  100,
                  100
                ],
                "ix": 3
              },
              "sk": {
                "a": 0,
                "k": 0,
                "ix": 4
              },
              "p": {
                "a": 0,
                "k": [
                  0,
                  0
                ],
                "ix": 2
              },
              "r": {
                "a": 0,
                "k": 0,
                "ix": 6
              },
              "sa": {
                "a": 0,
                "k": 0,
                "ix": 5
              },
              "o": {
                "a": 0,
                "k": 100,
                "ix": 7
              }
            }
          ]
        },
        {
          "ty": "fl",
          "bm": 0,
          "hd": false,
          "nm": "Fill 1",
          "c": {
            "a": 0,
            "k": [
              1,
              0.149,
              0.8
            ],
            "ix": 4
          },
          "r": 1,
          "o": {
            "a": 0,
            "k": 100,
            "ix": 5
          }
        }
      ],
      "ind": 5,
      "parent": 8
    },
    {
      "ty": 4,
      "nm": "Contour",
      "sr": 1,
      "st": 0,
      "op": 120,
      "ip": 0,
      "hd": false,
      "ddd": 0,
      "bm": 0,
      "tt": 1,
      "hasMask": false,
      "ao": 0,
      "ks": {
        "a": {
          "a": 0,
          "k": [
            -1,
            -145,
            0
          ],
          "ix": 1
        },
        "s": {
          "a": 0,
          "k": [
            100,
            100,
            100
          ],
          "ix": 6
        },
        "sk": {
          "a": 0,
          "k": 0
        },
        "p": {
          "a": 1,
          "k": [
            {
              "o": {
                "x": 0.31,
                "y": 0
              },
              "i": {
                "x": 0.69,
                "y": 1
              },
              "s": [
                -93,
                -145,
                0
              ],
              "t": 34,
              "ti": [
                -28.667,
                0,
                0
              ],
              "to": [
                28.667,
                0,
                0
              ]
            },
            {
              "s": [
                79,
                -145,
                0
              ],
              "t": 67
            }
          ],
          "ix": 2
        },
        "r": {
          "a": 0,
          "k": 0,
          "ix": 10
        },
        "sa": {
          "a": 0,
          "k": 0
        },
        "o": {
          "a": 0,
          "k": 100,
          "ix": 11
        }
      },
      "ef": [],
      "shapes": [
        {
          "ty": "gr",
          "bm": 0,
          "hd": false,
          "nm": "Shape 1",
          "ix": 1,
          "cix": 2,
          "it": [
            {
              "ty": "sh",
              "bm": 0,
              "hd": false,
              "nm": "Path 1",
              "ix": 1,
              "d": 1,
              "ks": {
                "a": 0,
                "k": {
                  "c": false,
                  "i": [
                    [
                      0,
                      0
                    ],
                    [
                      -34.81,
                      2.368
                    ],
                    [
                      0,
                      0
                    ]
                  ],
                  "o": [
                    [
                      0,
                      0
                    ],
                    [
                      35.381,
                      -2.407
                    ],
                    [
                      0,
                      0
                    ]
                  ],
                  "v": [
                    [
                      -28,
                      -176
                    ],
                    [
                      1,
                      -114
                    ],
                    [
                      37.607,
                      -188.159
                    ]
                  ]
                },
                "ix": 2
              }
            },
            {
              "ty": "st",
              "bm": 0,
              "hd": false,
              "nm": "Stroke 1",
              "lc": 1,
              "lj": 1,
              "ml": 4,
              "o": {
                "a": 0,
                "k": 100,
                "ix": 4
              },
              "w": {
                "a": 0,
                "k": 16,
                "ix": 5,
                "x": "var $bm_rt;\n$bm_rt = thisComp.layer('Main Stroke width - Color Ctrl').effect('Stroke width')('Slider');"
              },
              "c": {
                "a": 0,
                "k": [
                  1,
                  0.149,
                  0.8
                ],
                "ix": 3
              }
            },
            {
              "ty": "tr",
              "a": {
                "a": 0,
                "k": [
                  0,
                  0
                ],
                "ix": 1
              },
              "s": {
                "a": 0,
                "k": [
                  100,
                  100
                ],
                "ix": 3
              },
              "sk": {
                "a": 0,
                "k": 0,
                "ix": 4
              },
              "p": {
                "a": 0,
                "k": [
                  0,
                  0
                ],
                "ix": 2
              },
              "r": {
                "a": 0,
                "k": 0,
                "ix": 6
              },
              "sa": {
                "a": 0,
                "k": 0,
                "ix": 5
              },
              "o": {
                "a": 0,
                "k": 100,
                "ix": 7
              }
            }
          ]
        }
      ],
      "ind": 6,
      "parent": 8
    },
    {
      "ty": 4,
      "nm": "Base 2",
      "sr": 1,
      "st": 0,
      "op": 120,
      "ip": 0,
      "hd": false,
      "ddd": 0,
      "bm": 0,
      "hasMask": false,
      "td": 1,
      "ao": 0,
      "ks": {
        "a": {
          "a": 0,
          "k": [
            0,
            183.75,
            0
          ],
          "ix": 1
        },
        "s": {
          "a": 0,
          "k": [
            100,
            100,
            100
          ],
          "ix": 6
        },
        "sk": {
          "a": 0,
          "k": 0
        },
        "p": {
          "a": 0,
          "k": [
            50,
            233.75,
            0
          ],
          "ix": 2
        },
        "r": {
          "a": 1,
          "k": [
            {
              "o": {
                "x": 0.31,
                "y": 0
              },
              "i": {
                "x": 0.69,
                "y": 1
              },
              "s": [
                0
              ],
              "t": 0
            },
            {
              "o": {
                "x": 0.31,
                "y": 0
              },
              "i": {
                "x": 0.69,
                "y": 1
              },
              "s": [
                -21.024
              ],
              "t": 28
            },
            {
              "o": {
                "x": 0.31,
                "y": 0
              },
              "i": {
                "x": 0.69,
                "y": 1
              },
              "s": [
                10
              ],
              "t": 47
            },
            {
              "o": {
                "x": 0.31,
                "y": 0
              },
              "i": {
                "x": 0.69,
                "y": 1
              },
              "s": [
                -5
              ],
              "t": 62
            },
            {
              "o": {
                "x": 0.31,
                "y": 0
              },
              "i": {
                "x": 0.69,
                "y": 1
              },
              "s": [
                2.5
              ],
              "t": 73
            },
            {
              "s": [
                0
              ],
              "t": 83
            }
          ],
          "ix": 10
        },
        "sa": {
          "a": 0,
          "k": 0
        },
        "o": {
          "a": 0,
          "k": 100,
          "ix": 11
        }
      },
      "ef": [],
      "shapes": [
        {
          "ty": "gr",
          "bm": 0,
          "hd": false,
          "nm": "Group 1",
          "ix": 1,
          "cix": 2,
          "it": [
            {
              "ty": "sh",
              "bm": 0,
              "hd": false,
              "nm": "Path 1",
              "ix": 1,
              "d": 1,
              "ks": {
                "a": 0,
                "k": {
                  "c": true,
                  "i": [
                    [
                      0,
                      0
                    ],
                    [
                      0,
                      0
                    ],
                    [
                      0,
                      0
                    ],
                    [
                      0,
                      0
                    ]
                  ],
                  "o": [
                    [
                      0,
                      0
                    ],
                    [
                      0,
                      0
                    ],
                    [
                      0,
                      0
                    ],
                    [
                      0,
                      0
                    ]
                  ],
                  "v": [
                    [
                      43.078,
                      -62.671
                    ],
                    [
                      -42.316,
                      -62.671
                    ],
                    [
                      -42.316,
                      30.498
                    ],
                    [
                      43.078,
                      30.498
                    ]
                  ]
                },
                "ix": 2
              }
            },
            {
              "ty": "st",
              "bm": 0,
              "hd": false,
              "nm": "Stroke 1",
              "lc": 2,
              "lj": 2,
              "ml": 1,
              "o": {
                "a": 0,
                "k": 100,
                "ix": 4
              },
              "w": {
                "a": 0,
                "k": 16,
                "ix": 5,
                "x": "var $bm_rt;\n$bm_rt = thisComp.layer('Main Stroke width - Color Ctrl').effect('Stroke width')('Slider');"
              },
              "c": {
                "a": 0,
                "k": [
                  1,
                  1,
                  1
                ],
                "ix": 3
              }
            },
            {
              "ty": "tr",
              "a": {
                "a": 0,
                "k": [
                  0,
                  0
                ],
                "ix": 1
              },
              "s": {
                "a": 0,
                "k": [
                  100,
                  100
                ],
                "ix": 3
              },
              "sk": {
                "a": 0,
                "k": 0,
                "ix": 4
              },
              "p": {
                "a": 0,
                "k": [
                  0,
                  0
                ],
                "ix": 2
              },
              "r": {
                "a": 0,
                "k": 0,
                "ix": 6
              },
              "sa": {
                "a": 0,
                "k": 0,
                "ix": 5
              },
              "o": {
                "a": 0,
                "k": 100,
                "ix": 7
              }
            }
          ]
        },
        {
          "ty": "gr",
          "bm": 0,
          "hd": false,
          "nm": "Group 2",
          "ix": 2,
          "cix": 2,
          "it": [
            {
              "ty": "sh",
              "bm": 0,
              "hd": false,
              "nm": "Path 1",
              "ix": 1,
              "d": 1,
              "ks": {
                "a": 0,
                "k": {
                  "c": true,
                  "i": [
                    [
                      0,
                      0
                    ],
                    [
                      0,
                      0
                    ],
                    [
                      0,
                      0
                    ],
                    [
                      0,
                      0
                    ]
                  ],
                  "o": [
                    [
                      0,
                      0
                    ],
                    [
                      0,
                      0
                    ],
                    [
                      0,
                      0
                    ],
                    [
                      0,
                      0
                    ]
                  ],
                  "v": [
                    [
                      67.477,
                      73.195
                    ],
                    [
                      -66.714,
                      73.195
                    ],
                    [
                      -54.515,
                      30.498
                    ],
                    [
                      55.277,
                      30.498
                    ]
                  ]
                },
                "ix": 2
              }
            },
            {
              "ty": "st",
              "bm": 0,
              "hd": false,
              "nm": "Stroke 1",
              "lc": 2,
              "lj": 2,
              "ml": 1,
              "o": {
                "a": 0,
                "k": 100,
                "ix": 4
              },
              "w": {
                "a": 0,
                "k": 16,
                "ix": 5,
                "x": "var $bm_rt;\n$bm_rt = thisComp.layer('Main Stroke width - Color Ctrl').effect('Stroke width')('Slider');"
              },
              "c": {
                "a": 0,
                "k": [
                  1,
                  1,
                  1
                ],
                "ix": 3
              }
            },
            {
              "ty": "tr",
              "a": {
                "a": 0,
                "k": [
                  0,
                  0
                ],
                "ix": 1
              },
              "s": {
                "a": 0,
                "k": [
                  100,
                  100
                ],
                "ix": 3
              },
              "sk": {
                "a": 0,
                "k": 0,
                "ix": 4
              },
              "p": {
                "a": 0,
                "k": [
                  0,
                  0
                ],
                "ix": 2
              },
              "r": {
                "a": 0,
                "k": 0,
                "ix": 6
              },
              "sa": {
                "a": 0,
                "k": 0,
                "ix": 5
              },
              "o": {
                "a": 0,
                "k": 100,
                "ix": 7
              }
            }
          ]
        },
        {
          "ty": "gr",
          "bm": 0,
          "hd": false,
          "nm": "Group 3",
          "ix": 3,
          "cix": 2,
          "it": [
            {
              "ty": "sh",
              "bm": 0,
              "hd": false,
              "nm": "Path 1",
              "ix": 1,
              "d": 1,
              "ks": {
                "a": 0,
                "k": {
                  "c": true,
                  "i": [
                    [
                      16.844,
                      0
                    ],
                    [
                      0,
                      0
                    ],
                    [
                      0,
                      16.844
                    ],
                    [
                      0,
                      0
                    ],
                    [
                      0,
                      0
                    ],
                    [
                      0,
                      0
                    ]
                  ],
                  "o": [
                    [
                      0,
                      0
                    ],
                    [
                      -16.844,
                      0
                    ],
                    [
                      0,
                      0
                    ],
                    [
                      0,
                      0
                    ],
                    [
                      0,
                      0
                    ],
                    [
                      0,
                      16.844
                    ]
                  ],
                  "v": [
                    [
                      49.178,
                      183.75
                    ],
                    [
                      -49.178,
                      183.75
                    ],
                    [
                      -79.676,
                      153.252
                    ],
                    [
                      -79.676,
                      73.195
                    ],
                    [
                      79.676,
                      73.195
                    ],
                    [
                      79.676,
                      153.252
                    ]
                  ]
                },
                "ix": 2
              }
            },
            {
              "ty": "st",
              "bm": 0,
              "hd": false,
              "nm": "Stroke 1",
              "lc": 2,
              "lj": 2,
              "ml": 1,
              "o": {
                "a": 0,
                "k": 100,
                "ix": 4
              },
              "w": {
                "a": 0,
                "k": 16,
                "ix": 5,
                "x": "var $bm_rt;\n$bm_rt = thisComp.layer('Main Stroke width - Color Ctrl').effect('Stroke width')('Slider');"
              },
              "c": {
                "a": 0,
                "k": [
                  1,
                  1,
                  1
                ],
                "ix": 3
              }
            },
            {
              "ty": "tr",
              "a": {
                "a": 0,
                "k": [
                  0,
                  0
                ],
                "ix": 1
              },
              "s": {
                "a": 0,
                "k": [
                  100,
                  100
                ],
                "ix": 3
              },
              "sk": {
                "a": 0,
                "k": 0,
                "ix": 4
              },
              "p": {
                "a": 0,
                "k": [
                  0,
                  0
                ],
                "ix": 2
              },
              "r": {
                "a": 0,
                "k": 0,
                "ix": 6
              },
              "sa": {
                "a": 0,
                "k": 0,
                "ix": 5
              },
              "o": {
                "a": 0,
                "k": 100,
                "ix": 7
              }
            }
          ]
        },
        {
          "ty": "fl",
          "bm": 0,
          "hd": false,
          "nm": "Fill 1",
          "c": {
            "a": 0,
            "k": [
              1,
              0.149,
              0.8
            ],
            "ix": 4
          },
          "r": 1,
          "o": {
            "a": 0,
            "k": 100,
            "ix": 5
          }
        }
      ],
      "ind": 7,
      "parent": 1
    },
    {
      "ty": 4,
      "nm": "Lipstick",
      "sr": 1,
      "st": 0,
      "op": 120,
      "ip": 0,
      "hd": false,
      "ddd": 0,
      "bm": 0,
      "tt": 2,
      "hasMask": false,
      "ao": 0,
      "ks": {
        "a": {
          "a": 0,
          "k": [
            0,
            0,
            0
          ],
          "ix": 1
        },
        "s": {
          "a": 0,
          "k": [
            100,
            100,
            100
          ],
          "ix": 6
        },
        "sk": {
          "a": 0,
          "k": 0
        },
        "p": {
          "a": 1,
          "k": [
            {
              "o": {
                "x": 0.31,
                "y": 0
              },
              "i": {
                "x": 0.69,
                "y": 1
              },
              "s": [
                0,
                0,
                0
              ],
              "t": 0,
              "ti": [
                0,
                0,
                0
              ],
              "to": [
                0,
                21.5,
                0
              ]
            },
            {
              "o": {
                "x": 0.31,
                "y": 0
              },
              "i": {
                "x": 0.69,
                "y": 1
              },
              "s": [
                0,
                129,
                0
              ],
              "t": 21,
              "ti": [
                0,
                21.5,
                0
              ],
              "to": [
                0,
                0,
                0
              ]
            },
            {
              "s": [
                0,
                0,
                0
              ],
              "t": 51
            }
          ],
          "ix": 2
        },
        "r": {
          "a": 0,
          "k": 0,
          "ix": 10
        },
        "sa": {
          "a": 0,
          "k": 0
        },
        "o": {
          "a": 0,
          "k": 100,
          "ix": 11
        }
      },
      "ef": [],
      "shapes": [
        {
          "ty": "gr",
          "bm": 0,
          "hd": false,
          "nm": "Group 1",
          "ix": 1,
          "cix": 2,
          "it": [
            {
              "ty": "sh",
              "bm": 0,
              "hd": false,
              "nm": "Path 1",
              "ix": 1,
              "d": 1,
              "ks": {
                "a": 1,
                "k": [
                  {
                    "o": {
                      "x": 0.167,
                      "y": 0.167
                    },
                    "i": {
                      "x": 0.833,
                      "y": 0.833
                    },
                    "s": [
                      {
                        "c": true,
                        "i": [
                          [
                            0,
                            0
                          ],
                          [
                            0,
                            0
                          ],
                          [
                            0,
                            0
                          ],
                          [
                            0,
                            0
                          ]
                        ],
                        "o": [
                          [
                            0,
                            0
                          ],
                          [
                            0,
                            0
                          ],
                          [
                            0,
                            0
                          ],
                          [
                            0,
                            0
                          ]
                        ],
                        "v": [
                          [
                            -30.117,
                            -62.671
                          ],
                          [
                            -30.117,
                            -183.75
                          ],
                          [
                            30.879,
                            -158.589
                          ],
                          [
                            30.879,
                            -62.671
                          ]
                        ]
                      }
                    ],
                    "t": 0
                  },
                  {
                    "o": {
                      "x": 0.167,
                      "y": 0.167
                    },
                    "i": {
                      "x": 0.833,
                      "y": 0.833
                    },
                    "s": [
                      {
                        "c": true,
                        "i": [
                          [
                            0,
                            0
                          ],
                          [
                            0,
                            0
                          ],
                          [
                            0,
                            0
                          ],
                          [
                            0,
                            0
                          ]
                        ],
                        "o": [
                          [
                            0,
                            0
                          ],
                          [
                            0,
                            0
                          ],
                          [
                            0,
                            0
                          ],
                          [
                            0,
                            0
                          ]
                        ],
                        "v": [
                          [
                            -30.117,
                            -62.671
                          ],
                          [
                            -30.233,
                            -145.25
                          ],
                          [
                            30.758,
                            -183.089
                          ],
                          [
                            30.879,
                            -62.671
                          ]
                        ]
                      }
                    ],
                    "t": 14
                  },
                  {
                    "o": {
                      "x": 0.167,
                      "y": 0.167
                    },
                    "i": {
                      "x": 0.833,
                      "y": 0.833
                    },
                    "s": [
                      {
                        "c": true,
                        "i": [
                          [
                            0,
                            0
                          ],
                          [
                            0,
                            0
                          ],
                          [
                            0,
                            0
                          ],
                          [
                            0,
                            0
                          ]
                        ],
                        "o": [
                          [
                            0,
                            0
                          ],
                          [
                            0,
                            0
                          ],
                          [
                            0,
                            0
                          ],
                          [
                            0,
                            0
                          ]
                        ],
                        "v": [
                          [
                            -30.117,
                            -62.671
                          ],
                          [
                            -30.154,
                            -171.375
                          ],
                          [
                            30.84,
                            -166.464
                          ],
                          [
                            30.879,
                            -62.671
                          ]
                        ]
                      }
                    ],
                    "t": 28
                  },
                  {
                    "o": {
                      "x": 0.167,
                      "y": 0.167
                    },
                    "i": {
                      "x": 0.833,
                      "y": 0.833
                    },
                    "s": [
                      {
                        "c": true,
                        "i": [
                          [
                            0,
                            0
                          ],
                          [
                            0,
                            0
                          ],
                          [
                            0,
                            0
                          ],
                          [
                            0,
                            0
                          ]
                        ],
                        "o": [
                          [
                            0,
                            0
                          ],
                          [
                            0,
                            0
                          ],
                          [
                            0,
                            0
                          ],
                          [
                            0,
                            0
                          ]
                        ],
                        "v": [
                          [
                            -30.117,
                            -62.671
                          ],
                          [
                            -30.117,
                            -183.75
                          ],
                          [
                            30.879,
                            -158.589
                          ],
                          [
                            30.879,
                            -62.671
                          ]
                        ]
                      }
                    ],
                    "t": 47
                  },
                  {
                    "o": {
                      "x": 0.167,
                      "y": 0.167
                    },
                    "i": {
                      "x": 0.833,
                      "y": 0.833
                    },
                    "s": [
                      {
                        "c": true,
                        "i": [
                          [
                            0,
                            0
                          ],
                          [
                            0,
                            0
                          ],
                          [
                            0,
                            0
                          ],
                          [
                            0,
                            0
                          ]
                        ],
                        "o": [
                          [
                            0,
                            0
                          ],
                          [
                            0,
                            0
                          ],
                          [
                            0,
                            0
                          ],
                          [
                            0,
                            0
                          ]
                        ],
                        "v": [
                          [
                            -30.117,
                            -62.671
                          ],
                          [
                            -30.233,
                            -145.25
                          ],
                          [
                            30.758,
                            -183.089
                          ],
                          [
                            30.879,
                            -62.671
                          ]
                        ]
                      }
                    ],
                    "t": 62
                  },
                  {
                    "s": [
                      {
                        "c": true,
                        "i": [
                          [
                            0,
                            0
                          ],
                          [
                            0,
                            0
                          ],
                          [
                            0,
                            0
                          ],
                          [
                            0,
                            0
                          ]
                        ],
                        "o": [
                          [
                            0,
                            0
                          ],
                          [
                            0,
                            0
                          ],
                          [
                            0,
                            0
                          ],
                          [
                            0,
                            0
                          ]
                        ],
                        "v": [
                          [
                            -30.117,
                            -62.671
                          ],
                          [
                            -30.117,
                            -183.75
                          ],
                          [
                            30.879,
                            -158.589
                          ],
                          [
                            30.879,
                            -62.671
                          ]
                        ]
                      }
                    ],
                    "t": 83
                  }
                ],
                "ix": 2
              }
            },
            {
              "ty": "st",
              "bm": 0,
              "hd": false,
              "nm": "Stroke 1",
              "lc": 2,
              "lj": 2,
              "ml": 1,
              "o": {
                "a": 0,
                "k": 100,
                "ix": 4
              },
              "w": {
                "a": 0,
                "k": 16,
                "ix": 5,
                "x": "var $bm_rt;\n$bm_rt = thisComp.layer('Main Stroke width - Color Ctrl').effect('Stroke width')('Slider');"
              },
              "c": {
                "a": 0,
                "k": [
                  1,
                  0.149,
                  0.8
                ],
                "ix": 3
              }
            },
            {
              "ty": "tr",
              "a": {
                "a": 0,
                "k": [
                  0,
                  0
                ],
                "ix": 1
              },
              "s": {
                "a": 0,
                "k": [
                  100,
                  100
                ],
                "ix": 3
              },
              "sk": {
                "a": 0,
                "k": 0,
                "ix": 4
              },
              "p": {
                "a": 0,
                "k": [
                  0,
                  0
                ],
                "ix": 2
              },
              "r": {
                "a": 0,
                "k": 0,
                "ix": 6
              },
              "sa": {
                "a": 0,
                "k": 0,
                "ix": 5
              },
              "o": {
                "a": 0,
                "k": 100,
                "ix": 7
              }
            }
          ]
        }
      ],
      "ind": 8,
      "parent": 4
    },
    {
      "ty": 3,
      "nm": "Zero | troke width - Color Ctrl",
      "sr": 1,
      "st": 0,
      "op": 120,
      "ip": 0,
      "hd": false,
      "ddd": 0,
      "bm": 0,
      "hasMask": false,
      "ao": 0,
      "ks": {
        "a": {
          "a": 0,
          "k": [
            0,
            0,
            0
          ],
          "ix": 1
        },
        "s": {
          "a": 0,
          "k": [
            100,
            100,
            100
          ],
          "ix": 6
        },
        "sk": {
          "a": 0,
          "k": 0
        },
        "p": {
          "a": 0,
          "k": [
            250,
            250,
            0
          ],
          "ix": 2
        },
        "r": {
          "a": 0,
          "k": 0,
          "ix": 10
        },
        "sa": {
          "a": 0,
          "k": 0
        },
        "o": {
          "a": 0,
          "k": 0,
          "ix": 11
        }
      },
      "ef": [],
      "ind": 9
    }
  ],
  "v": "5.8.1",
  "fr": 60,
  "op": 120,
  "ip": 0,
  "assets": []
}